MANIFEST.in
README.markdown
setup.py
django_sld.egg-info/PKG-INFO
django_sld.egg-info/SOURCES.txt
django_sld.egg-info/dependency_links.txt
django_sld.egg-info/top_level.txt
djsld/__init__.py
djsld/epydoc.config
djsld/generator.py
djsld/tests/__init__.py
djsld/tests/manage.py
djsld/tests/settings.py
djsld/tests/djsld-test/__init__.py
djsld/tests/djsld-test/models.py
djsld/tests/djsld-test/tests.py