Metadata-Version: 1.1
Name: django-sld
Version: 1.0.5
Summary: A simple django library that generates SLD documents from geographic models.
Home-page: http://github.com/azavea/django-sld/
Author: David Zwarg
Author-email: dzwarg@azavea.com
License: Apache 2.0
Keywords: ogc sld geo geoserver mapserver osgeo geodjango
Platform: UNKNOWN
Classifier: Development Status :: 4 - Beta
Classifier: Intended Audience :: Developers
Classifier: License :: OSI Approved :: Apache Software License
Classifier: Programming Language :: Python
Classifier: Topic :: Scientific/Engineering :: GIS
Requires: python_sld
Requires: pysal
Requires: scipy
Requires: numpy
